MANIFEST.in
README.rst
setup.py
skeleprint_ui/SkelePrint_UI.py
skeleprint_ui/__init__.py
skeleprint_ui/__main__.py
skeleprint_ui/dimensions.jpg
skeleprint_ui/theta.jpg
skeleprint_ui/tpg_gui.py
skeleprint_ui/tpg_gui_support.py
skeleprint_ui.egg-info/PKG-INFO
skeleprint_ui.egg-info/SOURCES.txt
skeleprint_ui.egg-info/dependency_links.txt
skeleprint_ui.egg-info/not-zip-safe
skeleprint_ui.egg-info/requires.txt
skeleprint_ui.egg-info/top_level.txt