Metadata-Version: 1.0
Name: skeleprint-ui
Version: 1.16
Summary: SkelePrint Tool Path Generator
Home-page: http://github.com/shubhjagani/skeleprint_ui
Author: Shubh Jagani
Author-email: shubh.jagani@gmail.com
License: MIT
Platform: UNKNOWN
